poly_igdbpy/__init__.py
poly_igdbpy/igdbclient.py
poly_igdbpy/igdbgame.py
poly_igdbpy-0.1.2.dist-info/LICENSE
poly_igdbpy-0.1.2.dist-info/METADATA
poly_igdbpy-0.1.2.dist-info/WHEEL
poly_igdbpy-0.1.2.dist-info/top_level.txt
poly_igdbpy-0.1.2.dist-info/RECORD
